kedatatext/__init__.py
kedatatext/app.py
kedatatext/cli.py
kedatatext/preprocessing.py
kedatatext/py.typed
kedatatext/vectorization.py
kedatatext-0.2.0.dist-info/LICENSE
kedatatext-0.2.0.dist-info/METADATA
kedatatext-0.2.0.dist-info/WHEEL
kedatatext-0.2.0.dist-info/entry_points.txt
kedatatext-0.2.0.dist-info/RECORD
